{
  "kind": "collectionType",
  "collectionName": "partners",
  "info": {
    "singularName": "partner",
    "pluralName": "partners",
    "displayName": "Sponsors",
    "description": ""
  },
  "options": {
    "draftAndPublish": true
  },
  "pluginOptions": {},
  "attributes": {
    "Type": {
      "type": "enumeration",
      "enum": [
        "Gold",
        "Silver",
        "Bronze",
        "Partner"
      ],
      "required": true
    },
    "Image": {
      "type": "media",
      "multiple": false,
      "required": true,
      "allowedTypes": [
        "images"
      ]
    },
    "Name": {
      "type": "string",
      "required": true
    },
    "Link": {
      "type": "text",
      "required": false
    },
    "Description": {
      "type": "text",
      "required": false
    }
  }
}
